pymanuf/__init__.py
pymanuf/manuf.txt
pymanuf/online.py
pymanuf-2026.2.1.dist-info/licenses/LICENSE.md
pymanuf-2026.2.1.dist-info/METADATA
pymanuf-2026.2.1.dist-info/WHEEL
pymanuf-2026.2.1.dist-info/top_level.txt
pymanuf-2026.2.1.dist-info/RECORD
