Metadata-Version: 2.4
Name: pymanuf
Version: 2026.2.1
Summary: 📇 A very simple Python library to get the manufacturer of a specific MAC address
Author-email: Krypton <root@krypton.ninja>
License: MIT License
Project-URL: Homepage, https://github.com/kkrypt0nn/pymanuf
Project-URL: Issues, https://github.com/kkrypt0nn/pymanuf/issues
Project-URL: Source, https://github.com/kkrypt0nn/pymanuf
Keywords: networking,networks,mac address,manufacturer,mac address manufacturer
Classifier: Intended Audience :: Developers
Classifier: License :: OSI Approved :: MIT License
Classifier: Operating System :: OS Independent
Classifier: Programming Language :: Python :: 3
Classifier: Programming Language :: Python :: 3.9
Classifier: Programming Language :: Python :: 3.10
Classifier: Programming Language :: Python :: 3.11
Classifier: Programming Language :: Python :: 3.12
Classifier: Programming Language :: Python :: 3.13
Classifier: Topic :: System :: Networking
Requires-Python: >=3.9
License-File: LICENSE.md
Requires-Dist: requests
Dynamic: license-file
